src/.DS_Store
src/.summary_statistics.py.swo
src/__init__.py
src/config.py
src/mea_analyzer.py
src/summary_statistics.py
src/Axion/Annotation.m
src/Axion/AxionBioSystems_Matlab_guide.pdf
src/Axion/AxisFile.m
src/Axion/BlockVectorData.m
src/Axion/BlockVectorDataType.m
src/Axion/BlockVectorHeader.m
src/Axion/BlockVectorHeaderExtension.m
src/Axion/BlockVectorLegacyLoader.m
src/Axion/BlockVectorSet.m
src/Axion/CRC32.m
src/Axion/ChannelArray.m
src/Axion/ChannelMapping.m
src/Axion/DateTime.m
src/Axion/Entry.m
src/Axion/EntryRecord.m
src/Axion/EntryRecordID.m
src/Axion/EventTag.m
src/Axion/LegacySupport.m
src/Axion/LoadArgs.m
src/Axion/Note.m
src/Axion/PlateTypes.m
src/Axion/Spike_v1.m
src/Axion/StimulationChannels.m
src/Axion/StimulationEvent.m
src/Axion/StimulationEventData.m
src/Axion/StimulationWaveform.m
src/Axion/Tag.m
src/Axion/TagEntry.m
src/Axion/TagType.m
src/Axion/Waveform.m
src/Axion/WellInformation.m
src/Axion/calc_spike_rate.m
src/Axion/freadstring.m
src/Axion/load_AxIS_file.m
src/Axion/parseGuid.m
src/functions/.DS_Store
src/functions/MEA_convert.m
src/functions/MEA_process.m
src/functions/MEA_summary.m
src/functions/compute_nEEGfeats.m
src/functions/compute_peakfeats.m
src/functions/p1_convertpreprocess.m
src/p_util/__init__.py
src/p_util/old_util.py
src/p_util/plots.py
src/p_util/preprocessing.py
src/p_util/spike_detection.py
neurosum-0.0.0.5.dist-info/LICENSE
neurosum-0.0.0.5.dist-info/METADATA
neurosum-0.0.0.5.dist-info/WHEEL
neurosum-0.0.0.5.dist-info/entry_points.txt
neurosum-0.0.0.5.dist-info/top_level.txt
neurosum-0.0.0.5.dist-info/RECORD
