Metadata-Version: 2.1
Name: neurosum
Version: 0.0.0.5
Summary: Runs a statistical summary for electrophysiology data.
Home-page: https://github.com/
Author-email: lehenry@ucsd.edu
License: UNKNOWN
Platform: UNKNOWN
Classifier: Programming Language :: Python :: 3
Classifier: License :: OSI Approved :: MIT License
Classifier: Operating System :: OS Independent
Requires-Python: >=3.7
Requires-Dist: numpy
Requires-Dist: matplotlib
Requires-Dist: statsmodels
Requires-Dist: neurodsp
Requires-Dist: scipy
Requires-Dist: pyopenephys
Requires-Dist: h5py
